setup.py
aimlLab23/PGM1.py
aimlLab23/PGM2.py
aimlLab23/PGM3.py
aimlLab23/PGM4.py
aimlLab23/PGM5.py
aimlLab23/PGM6.py
aimlLab23/PGM7.py
aimlLab23/PGM8.py
aimlLab23/PGM9.py
aimlLab23/__init__.py
aimlLab23.egg-info/PKG-INFO
aimlLab23.egg-info/SOURCES.txt
aimlLab23.egg-info/dependency_links.txt
aimlLab23.egg-info/not-zip-safe
aimlLab23.egg-info/top_level.txt