Metadata-Version: 2.1
Name: aimlLab23
Version: 0.1
Summary: ENJOY
Home-page: UNKNOWN
Author: ENJOY
License: UNKNOWN
Platform: UNKNOWN
